Metadata-Version: 2.1
Name: gold33423316
Version: 0.1
Summary: Library untuk menghitung golden ratio
Home-page: UNKNOWN
Author: Zaky
Author-email: muhammadzaky034@gmail.com
License: UNKNOWN
Platform: UNKNOWN
Classifier: Development Status :: 3 - Alpha
Classifier: Intended Audience :: Developers
Classifier: License :: OSI Approved :: MIT License
Classifier: Programming Language :: Python :: 3
Classifier: Programming Language :: Python :: 3.6
Classifier: Programming Language :: Python :: 3.7
Classifier: Programming Language :: Python :: 3.8
License-File: LICENSE
